faesm/__init__.py
faesm/esm.py
faesm/esmc.py
faesm/fa_utils.py
faesm/progen2.py
faesm/torch_utils.py
faesm-0.1.1.dist-info/LICENSE
faesm-0.1.1.dist-info/METADATA
faesm-0.1.1.dist-info/WHEEL
faesm-0.1.1.dist-info/top_level.txt
faesm-0.1.1.dist-info/zip-safe
faesm-0.1.1.dist-info/RECORD
