Metadata-Version: 2.1
Name: faesm
Version: 0.1.1
License: MIT
Keywords: LLM,PLM,protein language model
License-File: LICENSE
Requires-Dist: setuptools
Requires-Dist: torch
Requires-Dist: einops
Requires-Dist: transformers
Provides-Extra: flash-attn
Requires-Dist: flash_attn; extra == "flash-attn"
Provides-Extra: test
Requires-Dist: pytest; extra == "test"
Requires-Dist: numpy; extra == "test"
Requires-Dist: biopython; extra == "test"
Requires-Dist: matplotlib; extra == "test"
Requires-Dist: seaborn; extra == "test"
